unlimited_time/__init__.py
unlimited_time/time_utils.py
unlimited_time-0.1.0.dist-info/METADATA
unlimited_time-0.1.0.dist-info/WHEEL
unlimited_time-0.1.0.dist-info/top_level.txt
unlimited_time-0.1.0.dist-info/RECORD
